ip2country/interfaces.py
ip2country/parser.py
ip2country/utils.py
ip2country/__init__.py
ip2country/record.py
ip2country-0.1.1.dist-info/DESCRIPTION.rst
ip2country-0.1.1.dist-info/METADATA
ip2country-0.1.1.dist-info/metadata.json
ip2country-0.1.1.dist-info/top_level.txt
ip2country-0.1.1.dist-info/RECORD
ip2country-0.1.1.dist-info/WHEEL
