Metadata-Version: 2.0
Name: ip2country
Version: 0.1.1
Summary: Lookup country code (iso 3166) by IP address.
Home-page: https://github.com/yosida95/ip2country
Author: Kohei YOSHIDA
Author-email: license@yosida95.com
License: The MIT License (MIT) Copyright © 2014 Kohei YOSHIDA <license@yosida95.com>
